AUTHORS
LICENSE
MANIFEST.in
README.md
setup.py
django_smart_selects_generic.egg-info/PKG-INFO
django_smart_selects_generic.egg-info/SOURCES.txt
django_smart_selects_generic.egg-info/dependency_links.txt
django_smart_selects_generic.egg-info/requires.txt
django_smart_selects_generic.egg-info/top_level.txt
smart_generic/__init__.py
smart_generic/form_fields.py
smart_generic/forms.py
smart_generic/urls.py
smart_generic/views.py
smart_generic/widgets.py