Metadata-Version: 1.0
Name: django-smart-selects-generic
Version: 0.1.0
Summary: Django application to handle chained generic model fields.
Home-page: http://bitbucket.org/suvitorg/django-smart-selects-generic
Author: Victor Safronovich
Author-email: vsafronovich@gmail.com
License: UNKNOWN
Platform: UNKNOWN
